pynight/__init__.py
pynight/async_url.py
pynight/batched_iterable.py
pynight/common_anthropic.py
pynight/common_arxiv.py
pynight/common_async.py
pynight/common_attr.py
pynight/common_base64.py
pynight/common_bells.py
pynight/common_benchmark.py
pynight/common_clip.py
pynight/common_clipboard.py
pynight/common_combinatorics.py
pynight/common_condition.py
pynight/common_csv.py
pynight/common_datasets.py
pynight/common_datetime.py
pynight/common_debugging.py
pynight/common_debugging2.py
pynight/common_deepseek.py
pynight/common_dict.py
pynight/common_dynamic.py
pynight/common_evaluate.py
pynight/common_executing.py
pynight/common_external.py
pynight/common_faith.py
pynight/common_fastapi.py
pynight/common_feed.py
pynight/common_files.py
pynight/common_functional.py
pynight/common_fzf.py
pynight/common_gemini_tts.py
pynight/common_groq.py
pynight/common_hash.py
pynight/common_health.py
pynight/common_hf.py
pynight/common_hosts.py
pynight/common_icecream.py
pynight/common_ipython.py
pynight/common_iterable.py
pynight/common_jax.py
pynight/common_json.py
pynight/common_jupyter.py
pynight/common_latex.py
pynight/common_llm.py
pynight/common_lock_async.py
pynight/common_model_name.py
pynight/common_networking.py
pynight/common_numpy.py
pynight/common_obj.py
pynight/common_openai.py
pynight/common_package.py
pynight/common_plt.py
pynight/common_print.py
pynight/common_proxy.py
pynight/common_random.py
pynight/common_redirections.py
pynight/common_regex.py
pynight/common_rtl.py
pynight/common_seg.py
pynight/common_shell.py
pynight/common_sort.py
pynight/common_spacy.py
pynight/common_ss.py
pynight/common_str.py
pynight/common_telegram.py
pynight/common_threading.py
pynight/common_timm.py
pynight/common_together.py
pynight/common_torch.org
pynight/common_torch.py
pynight/common_tqdm.py
pynight/common_tqdm2.py
pynight/common_tui.py
pynight/common_uvicorn.py
pynight-0.2.4.dist-info/METADATA
pynight-0.2.4.dist-info/WHEEL
pynight-0.2.4.dist-info/entry_points.txt
pynight-0.2.4.dist-info/RECORD
