Metadata-Version: 2.4
Name: pynight
Version: 0.2.4
Summary: My Python utility library.
License: MIT
Author: NightMachinary
Author-email: rudiwillalwaysloveyou@gmail.com
Requires-Python: >=3.8,<4.0
Classifier: License :: OSI Approved :: MIT License
Classifier: Programming Language :: Python :: 3
Classifier: Programming Language :: Python :: 3.8
Classifier: Programming Language :: Python :: 3.9
Classifier: Programming Language :: Python :: 3.10
Classifier: Programming Language :: Python :: 3.11
Classifier: Programming Language :: Python :: 3.12
Classifier: Programming Language :: Python :: 3.13
Classifier: Programming Language :: Python :: 3.14
Requires-Dist: aiofile
Requires-Dist: brish (>=0.3.3,<0.4.0)
Requires-Dist: dnspython (>=2.1.0,<3.0.0)
Requires-Dist: executing (>=1.2.0,<2.0.0)
Requires-Dist: matplotlib (>=3.7.1,<4.0.0)
Requires-Dist: openai (>=1.14.2,<2.0.0)
Requires-Dist: pyperclip (>=1.8.2,<2.0.0)
Requires-Dist: spacy (>=3.5.1,<4.0.0)
Requires-Dist: tiktoken
